dyntree/__init__.py
tests/__init__.py
tests/test_dyntree.py
dyntree-0.0.1.dist-info/METADATA
dyntree-0.0.1.dist-info/WHEEL
dyntree-0.0.1.dist-info/top_level.txt
dyntree-0.0.1.dist-info/RECORD
