Metadata-Version: 2.1
Name: dyntree
Version: 0.0.1
Summary: Provides possibility to create and manage tree built by id and parent for every node
Home-page: https://bitbucket.org/submax82/dyntree
Author: Massimo Cavalleri
Author-email: submax@tiscali.it
License: UNKNOWN
Platform: any
Classifier: Intended Audience :: Developers
Classifier: License :: OSI Approved :: BSD License
Classifier: Operating System :: OS Independent
Classifier: Programming Language :: Python
Classifier: Topic :: Internet :: WWW/HTTP :: Dynamic Content
Classifier: Topic :: Software Development :: Libraries :: Python Modules
